iam_rolesanywhere_session/__init__.py
iam_rolesanywhere_session/iam_rolesanywhere_session.py
iam_rolesanywhere_session-2.3.0.dist-info/licenses/LICENSE
iam_rolesanywhere_session-2.3.0.dist-info/METADATA
iam_rolesanywhere_session-2.3.0.dist-info/WHEEL
iam_rolesanywhere_session-2.3.0.dist-info/top_level.txt
iam_rolesanywhere_session-2.3.0.dist-info/RECORD
