Metadata-Version: 2.4
Name: iam_rolesanywhere_session
Version: 2.3.0
Summary: Boto3 session creator for IAM Roles Anywhere
Author-email: Thomas Buatois <tbuatois@amazon.fr>
License: Apache-2.0
Project-URL: documentation, https://awslabs.github.io/iam-rolesanywhere-session/
Project-URL: repository, https://github.com/awslabs/iam-roles-anywhere-session.git
Project-URL: changelog, https://github.com/awslabs/iam-roles-anywhere-session./blob/main/CHANGELOG.md
Keywords: iam,aws,rolesanywhere,boto3,botocore
Classifier: Development Status :: 4 - Beta
Classifier: License :: OSI Approved :: Apache Software License
Classifier: Programming Language :: Python :: 3
Requires-Python: >=3.8
License-File: LICENSE
Requires-Dist: boto3>=1.24.55
Requires-Dist: botocore>=1.27.55
Requires-Dist: cryptography>=37.0.4
Requires-Dist: importlib-metadata; python_version < "3.8"
Provides-Extra: dev
Requires-Dist: mkdocs; extra == "dev"
Requires-Dist: mkdocs-material; extra == "dev"
Requires-Dist: mkdocstrings; extra == "dev"
Requires-Dist: mkdocstrings-python; extra == "dev"
Requires-Dist: pre-commit; extra == "dev"
Requires-Dist: pymdown-extensions; extra == "dev"
Requires-Dist: pytest; extra == "dev"
Dynamic: license-file
